<?xml version="1.0" encoding="UTF-8"?>
<metadata xml:lang="de"><Esri><CreaDate>20161130</CreaDate><CreaTime>15001500</CreaTime><SyncOnce>FALSE</SyncOnce><SyncDate>20161118</SyncDate><SyncTime>08363700</SyncTime><ModDate>20161118</ModDate><ModTime>08363700</ModTime><DataProperties><lineage><Process ToolSource="C:\Programme\ArcGIS\ArcToolbox\Toolboxes\Data Management Tools.tbx\CopyFeatures" Date="20101220" Time="085031">CopyFeatures d:\basisgeometrien\bkg_adv\admin_grenzen_ab1999\stand_31122002\vg1000\gem1000\region.gem D:\Temp\temp_kk\Geometrien\Stichtag_20021231\vg1000.gdb\gem1000_region_gem # 0 0 0</Process><Process ToolSource="c:\program files (x86)\arcgis\desktop10.4\ArcToolbox\Toolboxes\Data Management Tools.tbx\Copy" Date="20161027" Time="101435">Copy D:\Geodaten\Geometrien\Vermessungsverwaltung\Verwaltungsgebiete\Stichtag_20021231\Verwaltungsgebiete_1000.gdb\ETRS89_UTM32s\vg1000_gemeinden D:\GIS_IT\Wahlen\Bundestagswahl2002\Geodaten\DatenBTW2002.gdb\vg1000_gemeinden_20021231 FeatureClass</Process><Process ToolSource="c:\program files (x86)\arcgis\desktop10.4\ArcToolbox\Toolboxes\Data Management Tools.tbx\AddField" Date="20161027" Time="103125">AddField D:\GIS_IT\Wahlen\Bundestagswahl2002\Geodaten\DatenBTW2002.gdb\vg1000_gemeinden_20021231 TeilNr TEXT # # 2 # NULLABLE NON_REQUIRED #</Process><Process ToolSource="c:\program files (x86)\arcgis\desktop10.4\ArcToolbox\Toolboxes\Data Management Tools.tbx\AddField" Date="20161027" Time="103126">AddField D:\GIS_IT\Wahlen\Bundestagswahl2002\Geodaten\DatenBTW2002.gdb\vg1000_gemeinden_20021231 egem_index TEXT # # 10 # NULLABLE NON_REQUIRED #</Process><Process ToolSource="c:\program files (x86)\arcgis\desktop10.4\ArcToolbox\Toolboxes\Data Management Tools.tbx\AddField" Date="20161027" Time="103126">AddField D:\GIS_IT\Wahlen\Bundestagswahl2002\Geodaten\DatenBTW2002.gdb\vg1000_gemeinden_20021231 WKR_NR SHORT # # # # NULLABLE NON_REQUIRED #</Process><Process ToolSource="c:\program files (x86)\arcgis\desktop10.4\ArcToolbox\Toolboxes\Data Management Tools.tbx\CalculateField" Date="20161027" Time="110931">CalculateField vg1000_gemeinden_20021231 WKR_NR 239 VB #</Process><Process ToolSource="c:\program files (x86)\arcgis\desktop10.4\ArcToolbox\Toolboxes\Data Management Tools.tbx\CalculateField" Date="20161027" Time="111228">CalculateField vg1000_gemeinden_20021231 WKR_NR 240 VB #</Process><Process ToolSource="c:\program files (x86)\arcgis\desktop10.4\ArcToolbox\Toolboxes\Data Management Tools.tbx\CalculateField" Date="20161027" Time="111844">CalculateField vg1000_gemeinden_20021231 WKR_NR 238 VB #</Process><Process ToolSource="c:\program files (x86)\arcgis\desktop10.4\ArcToolbox\Toolboxes\Data Management Tools.tbx\CalculateField" Date="20161027" Time="112404">CalculateField vg1000_gemeinden_20021231 WKR_NR 237 VB #</Process><Process ToolSource="c:\program files (x86)\arcgis\desktop10.4\ArcToolbox\Toolboxes\Data Management Tools.tbx\CalculateField" Date="20161027" Time="112519">CalculateField vg1000_gemeinden_20021231 WKR_NR 249 VB #</Process><Process ToolSource="c:\program files (x86)\arcgis\desktop10.4\ArcToolbox\Toolboxes\Data Management Tools.tbx\CalculateField" Date="20161027" Time="112555">CalculateField vg1000_gemeinden_20021231 WKR_NR 251 VB #</Process><Process ToolSource="c:\program files (x86)\arcgis\desktop10.4\ArcToolbox\Toolboxes\Data Management Tools.tbx\CalculateField" Date="20161027" Time="112840">CalculateField vg1000_gemeinden_20021231 WKR_NR 249 VB #</Process><Process ToolSource="c:\program files (x86)\arcgis\desktop10.4\ArcToolbox\Toolboxes\Data Management Tools.tbx\CalculateField" Date="20161027" Time="113033">CalculateField vg1000_gemeinden_20021231 WKR_NR 250 VB #</Process><Process ToolSource="c:\program files (x86)\arcgis\desktop10.4\ArcToolbox\Toolboxes\Data Management Tools.tbx\CalculateField" Date="20161027" Time="113129">CalculateField vg1000_gemeinden_20021231 WKR_NR 248 VB #</Process><Process ToolSource="c:\program files (x86)\arcgis\desktop10.4\ArcToolbox\Toolboxes\Data Management Tools.tbx\CalculateField" Date="20161027" Time="113224">CalculateField vg1000_gemeinden_20021231 WKR_NR 252 VB #</Process><Process ToolSource="c:\program files (x86)\arcgis\desktop10.4\ArcToolbox\Toolboxes\Data Management Tools.tbx\CalculateField" Date="20161027" Time="113401">CalculateField vg1000_gemeinden_20021231 WKR_NR 243 VB #</Process><Process ToolSource="c:\program files (x86)\arcgis\desktop10.4\ArcToolbox\Toolboxes\Data Management Tools.tbx\CalculateField" Date="20161027" Time="113537">CalculateField vg1000_gemeinden_20021231 WKR_NR 247 VB #</Process><Process ToolSource="c:\program files (x86)\arcgis\desktop10.4\ArcToolbox\Toolboxes\Data Management Tools.tbx\CalculateField" Date="20161027" Time="113649">CalculateField vg1000_gemeinden_20021231 WKR_NR 233 VB #</Process><Process ToolSource="c:\program files (x86)\arcgis\desktop10.4\ArcToolbox\Toolboxes\Data Management Tools.tbx\CalculateField" Date="20161027" Time="113819">CalculateField vg1000_gemeinden_20021231 WKR_NR 236 VB #</Process><Process ToolSource="c:\program files (x86)\arcgis\desktop10.4\ArcToolbox\Toolboxes\Data Management Tools.tbx\CalculateField" Date="20161027" Time="113926">CalculateField vg1000_gemeinden_20021231 WKR_NR 235 VB #</Process><Process ToolSource="c:\program files (x86)\arcgis\desktop10.4\ArcToolbox\Toolboxes\Data Management Tools.tbx\CalculateField" Date="20161027" Time="114013">CalculateField vg1000_gemeinden_20021231 WKR_NR 234 VB #</Process><Process ToolSource="c:\program files (x86)\arcgis\desktop10.4\ArcToolbox\Toolboxes\Data Management Tools.tbx\CalculateField" Date="20161027" Time="114050">CalculateField vg1000_gemeinden_20021231 WKR_NR 229 VB #</Process><Process ToolSource="c:\program files (x86)\arcgis\desktop10.4\ArcToolbox\Toolboxes\Data Management Tools.tbx\CalculateField" Date="20161027" Time="114134">CalculateField vg1000_gemeinden_20021231 WKR_NR 215 VB #</Process><Process ToolSource="c:\program files (x86)\arcgis\desktop10.4\ArcToolbox\Toolboxes\Data Management Tools.tbx\CalculateField" Date="20161027" Time="114227">CalculateField vg1000_gemeinden_20021231 WKR_NR 228 VB #</Process><Process ToolSource="c:\program files (x86)\arcgis\desktop10.4\ArcToolbox\Toolboxes\Data Management Tools.tbx\CalculateField" Date="20161027" Time="114303">CalculateField vg1000_gemeinden_20021231 WKR_NR 226 VB #</Process><Process ToolSource="c:\program files (x86)\arcgis\desktop10.4\ArcToolbox\Toolboxes\Data Management Tools.tbx\CalculateField" Date="20161027" Time="114600">CalculateField vg1000_gemeinden_20021231 WKR_NR 223 VB #</Process><Process ToolSource="c:\program files (x86)\arcgis\desktop10.4\ArcToolbox\Toolboxes\Data Management Tools.tbx\CalculateField" Date="20161027" Time="114622">CalculateField vg1000_gemeinden_20021231 WKR_NR 225 VB #</Process><Process ToolSource="c:\program files (x86)\arcgis\desktop10.4\ArcToolbox\Toolboxes\Data Management Tools.tbx\CalculateField" Date="20161027" Time="114914">CalculateField vg1000_gemeinden_20021231 WKR_NR 256 VB #</Process><Process ToolSource="c:\program files (x86)\arcgis\desktop10.4\ArcToolbox\Toolboxes\Data Management Tools.tbx\CalculateField" Date="20161027" Time="144128">CalculateField vg1000_gemeinden_20021231 TeilNr "00" VB #</Process><Process ToolSource="c:\program files (x86)\arcgis\desktop10.4\ArcToolbox\Toolboxes\Data Management Tools.tbx\CalculateField" Date="20161027" Time="144417">CalculateField D:\GIS_IT\Wahlen\Bundestagswahl2002\Geodaten\DatenBTW2002.gdb\vg1000_gemeinden_20021231 egem_index "[KEY] &amp; [TeilNr]" VB #</Process><Process ToolSource="c:\program files (x86)\arcgis\desktop10.4\ArcToolbox\Toolboxes\Data Management Tools.tbx\AddField" Date="20161027" Time="145348">AddField D:\GIS_IT\Wahlen\Bundestagswahl2002\Geodaten\DatenBTW2002.gdb\vg1000_gemeinden_20021231 krs_index TEXT # # 5 # NULLABLE NON_REQUIRED #</Process><Process ToolSource="c:\program files (x86)\arcgis\desktop10.4\ArcToolbox\Toolboxes\Data Management Tools.tbx\CalculateField" Date="20161027" Time="145608">CalculateField D:\GIS_IT\Wahlen\Bundestagswahl2002\Geodaten\DatenBTW2002.gdb\vg1000_gemeinden_20021231 krs_index !KEY![:5] PYTHON_9.3 #</Process><Process ToolSource="c:\program files (x86)\arcgis\desktop10.4\ArcToolbox\Toolboxes\Data Management Tools.tbx\Dissolve" Date="20161027" Time="145843">Dissolve D:\GIS_IT\Wahlen\Bundestagswahl2002\Geodaten\DatenBTW2002.gdb\vg1000_gemeinden_20021231 D:\GIS_IT\Wahlen\Bundestagswahl2002\Geodaten\DatenBTW2002.gdb\krs_BTW2002 krs_index # MULTI_PART DISSOLVE_LINES</Process><Process ToolSource="c:\program files (x86)\arcgis\desktop10.4\ArcToolbox\Toolboxes\Analysis Tools.tbx\Union" Date="20161028" Time="104641">Union "D:\GIS_IT\Wahlen\Bundestagswahl2002\Geodaten\DatenBTW2002.gdb\krs_BTW2002 #;D:\GIS_IT\Wahlen\Bundestagswahl2002\Geodaten\DatenBTW2002.gdb\wkr_BTW2002 #" D:\GIS_IT\Wahlen\Bundestagswahl2002\Geodaten\DatenBTW2002.gdb\wkr_krs_BTW2002 ALL # GAPS</Process><Process ToolSource="c:\program files (x86)\arcgis\desktop10.4\ArcToolbox\Toolboxes\Cartography Tools.tbx\SimplifyPolygon" Date="20161028" Time="104933">SimplifyPolygon D:\GIS_IT\Wahlen\Bundestagswahl2002\Geodaten\DatenBTW2002.gdb\wkr_krs_BTW2002 D:\GIS_IT\Wahlen\Bundestagswahl2002\Geodaten\DatenBTW2002.gdb\wkr_krs_BTW2002_gen_org BEND_SIMPLIFY "2500 Meters" "0 SquareMeters" RESOLVE_ERRORS KEEP_COLLAPSED_POINTS</Process><Process ToolSource="c:\program files (x86)\arcgis\desktop10.4\ArcToolbox\Toolboxes\Data Management Tools.tbx\Dissolve" Date="20161117" Time="144046">Dissolve D:\GIS_IT\Wahlen\Bundestagswahl2002\Geodaten\DatenBTW2002.gdb\wkr_krs_BTW2002_gen D:\GIS_IT\Wahlen\Bundestagswahl2002\Geodaten\DatenBTW2002.gdb\wkr_BTW2002_gen WKR_NR # MULTI_PART DISSOLVE_LINES</Process><Process ToolSource="c:\program files (x86)\arcgis\desktop10.4\ArcToolbox\Toolboxes\Data Management Tools.tbx\AddField" Date="20161117" Time="144321">AddField D:\GIS_IT\Wahlen\Bundestagswahl2002\Geodaten\DatenBTW2002.gdb\wkr_BTW2002_gen WKR_NAME TEXT # # 90 # NULLABLE NON_REQUIRED #</Process><Process ToolSource="c:\program files (x86)\arcgis\desktop10.4\ArcToolbox\Toolboxes\Data Management Tools.tbx\AddField" Date="20161117" Time="144321">AddField D:\GIS_IT\Wahlen\Bundestagswahl2002\Geodaten\DatenBTW2002.gdb\wkr_BTW2002_gen LAND_NR TEXT # # 2 # NULLABLE NON_REQUIRED #</Process><Process ToolSource="c:\program files (x86)\arcgis\desktop10.4\ArcToolbox\Toolboxes\Data Management Tools.tbx\AddField" Date="20161117" Time="144321">AddField D:\GIS_IT\Wahlen\Bundestagswahl2002\Geodaten\DatenBTW2002.gdb\wkr_BTW2002_gen LAND_NAME TEXT # # 25 # NULLABLE NON_REQUIRED #</Process><Process ToolSource="c:\program files (x86)\arcgis\desktop10.4\ArcToolbox\Toolboxes\Data Management Tools.tbx\CalculateField" Date="20161118" Time="074221">CalculateField wkr_BTW2002_gen LAND_NR "01" VB #</Process><Process ToolSource="c:\program files (x86)\arcgis\desktop10.4\ArcToolbox\Toolboxes\Data Management Tools.tbx\CalculateField" Date="20161118" Time="074243">CalculateField wkr_BTW2002_gen LAND_NAME "Schleswig-Holstein" VB #</Process><Process ToolSource="c:\program files (x86)\arcgis\desktop10.4\ArcToolbox\Toolboxes\Data Management Tools.tbx\CalculateField" Date="20161118" Time="074328">CalculateField wkr_BTW2002_gen LAND_NR "13" VB #</Process><Process ToolSource="c:\program files (x86)\arcgis\desktop10.4\ArcToolbox\Toolboxes\Data Management Tools.tbx\CalculateField" Date="20161118" Time="074351">CalculateField wkr_BTW2002_gen LAND_NAME "Mecklenburg-Vorpommern" VB #</Process><Process ToolSource="c:\program files (x86)\arcgis\desktop10.4\ArcToolbox\Toolboxes\Data Management Tools.tbx\CalculateField" Date="20161118" Time="074431">CalculateField wkr_BTW2002_gen LAND_NR "02" VB #</Process><Process ToolSource="c:\program files (x86)\arcgis\desktop10.4\ArcToolbox\Toolboxes\Data Management Tools.tbx\CalculateField" Date="20161118" Time="074448">CalculateField wkr_BTW2002_gen LAND_NAME "Hamburg" VB #</Process><Process ToolSource="c:\program files (x86)\arcgis\desktop10.4\ArcToolbox\Toolboxes\Data Management Tools.tbx\CalculateField" Date="20161118" Time="074533">CalculateField wkr_BTW2002_gen LAND_NAME "Niedersachsen" VB #</Process><Process ToolSource="c:\program files (x86)\arcgis\desktop10.4\ArcToolbox\Toolboxes\Data Management Tools.tbx\CalculateField" Date="20161118" Time="074545">CalculateField wkr_BTW2002_gen LAND_NR "03" VB #</Process><Process ToolSource="c:\program files (x86)\arcgis\desktop10.4\ArcToolbox\Toolboxes\Data Management Tools.tbx\CalculateField" Date="20161118" Time="074614">CalculateField wkr_BTW2002_gen LAND_NR "04" VB #</Process><Process ToolSource="c:\program files (x86)\arcgis\desktop10.4\ArcToolbox\Toolboxes\Data Management Tools.tbx\CalculateField" Date="20161118" Time="074627">CalculateField wkr_BTW2002_gen LAND_NAME "Bremen" VB #</Process><Process ToolSource="c:\program files (x86)\arcgis\desktop10.4\ArcToolbox\Toolboxes\Data Management Tools.tbx\CalculateField" Date="20161118" Time="074714">CalculateField wkr_BTW2002_gen LAND_NR "Brandenburg" VB #</Process><Process ToolSource="c:\program files (x86)\arcgis\desktop10.4\ArcToolbox\Toolboxes\Data Management Tools.tbx\CalculateField" Date="20161118" Time="074725">CalculateField wkr_BTW2002_gen LAND_NAME "Brandenburg" VB #</Process><Process ToolSource="c:\program files (x86)\arcgis\desktop10.4\ArcToolbox\Toolboxes\Data Management Tools.tbx\CalculateField" Date="20161118" Time="074739">CalculateField wkr_BTW2002_gen LAND_NR "12" VB #</Process><Process ToolSource="c:\program files (x86)\arcgis\desktop10.4\ArcToolbox\Toolboxes\Data Management Tools.tbx\CalculateField" Date="20161118" Time="080608">CalculateField wkr_BTW2002_gen LAND_NR "15" VB #</Process><Process ToolSource="c:\program files (x86)\arcgis\desktop10.4\ArcToolbox\Toolboxes\Data Management Tools.tbx\CalculateField" Date="20161118" Time="080626">CalculateField wkr_BTW2002_gen LAND_NAME "Sachsen-Anhalt" VB #</Process><Process ToolSource="c:\program files (x86)\arcgis\desktop10.4\ArcToolbox\Toolboxes\Data Management Tools.tbx\CalculateField" Date="20161118" Time="082204">CalculateField wkr_BTW2002_gen LAND_NR "11" VB #</Process><Process ToolSource="c:\program files (x86)\arcgis\desktop10.4\ArcToolbox\Toolboxes\Data Management Tools.tbx\CalculateField" Date="20161118" Time="082221">CalculateField wkr_BTW2002_gen LAND_NAME "Berlin" VB #</Process><Process ToolSource="c:\program files (x86)\arcgis\desktop10.4\ArcToolbox\Toolboxes\Data Management Tools.tbx\CalculateField" Date="20161118" Time="082301">CalculateField wkr_BTW2002_gen LAND_NR "05" VB #</Process><Process ToolSource="c:\program files (x86)\arcgis\desktop10.4\ArcToolbox\Toolboxes\Data Management Tools.tbx\CalculateField" Date="20161118" Time="082329">CalculateField wkr_BTW2002_gen LAND_NAME "Nordrhein-Westfalen" VB #</Process><Process ToolSource="c:\program files (x86)\arcgis\desktop10.4\ArcToolbox\Toolboxes\Data Management Tools.tbx\CalculateField" Date="20161118" Time="082410">CalculateField wkr_BTW2002_gen LAND_NR "14" VB #</Process><Process ToolSource="c:\program files (x86)\arcgis\desktop10.4\ArcToolbox\Toolboxes\Data Management Tools.tbx\CalculateField" Date="20161118" Time="082431">CalculateField wkr_BTW2002_gen LAND_NAME "Sachsen" VB #</Process><Process ToolSource="c:\program files (x86)\arcgis\desktop10.4\ArcToolbox\Toolboxes\Data Management Tools.tbx\CalculateField" Date="20161118" Time="082517">CalculateField wkr_BTW2002_gen LAND_NR "06" VB #</Process><Process ToolSource="c:\program files (x86)\arcgis\desktop10.4\ArcToolbox\Toolboxes\Data Management Tools.tbx\CalculateField" Date="20161118" Time="082533">CalculateField wkr_BTW2002_gen LAND_NAME "Hessen" VB #</Process><Process ToolSource="c:\program files (x86)\arcgis\desktop10.4\ArcToolbox\Toolboxes\Data Management Tools.tbx\CalculateField" Date="20161118" Time="082611">CalculateField wkr_BTW2002_gen LAND_NR "16" VB #</Process><Process ToolSource="c:\program files (x86)\arcgis\desktop10.4\ArcToolbox\Toolboxes\Data Management Tools.tbx\CalculateField" Date="20161118" Time="082628">CalculateField wkr_BTW2002_gen LAND_NAME "Thüringen" VB #</Process><Process ToolSource="c:\program files (x86)\arcgis\desktop10.4\ArcToolbox\Toolboxes\Data Management Tools.tbx\CalculateField" Date="20161118" Time="082744">CalculateField wkr_BTW2002_gen LAND_NR "07" VB #</Process><Process ToolSource="c:\program files (x86)\arcgis\desktop10.4\ArcToolbox\Toolboxes\Data Management Tools.tbx\CalculateField" Date="20161118" Time="082808">CalculateField wkr_BTW2002_gen LAND_NAME "Rheinland-Pfalz" VB #</Process><Process ToolSource="c:\program files (x86)\arcgis\desktop10.4\ArcToolbox\Toolboxes\Data Management Tools.tbx\CalculateField" Date="20161118" Time="082849">CalculateField wkr_BTW2002_gen LAND_NR "09" VB #</Process><Process ToolSource="c:\program files (x86)\arcgis\desktop10.4\ArcToolbox\Toolboxes\Data Management Tools.tbx\CalculateField" Date="20161118" Time="082904">CalculateField wkr_BTW2002_gen LAND_NAME "Bayern" VB #</Process><Process ToolSource="c:\program files (x86)\arcgis\desktop10.4\ArcToolbox\Toolboxes\Data Management Tools.tbx\CalculateField" Date="20161118" Time="082946">CalculateField wkr_BTW2002_gen LAND_NR "08" VB #</Process><Process ToolSource="c:\program files (x86)\arcgis\desktop10.4\ArcToolbox\Toolboxes\Data Management Tools.tbx\CalculateField" Date="20161118" Time="083014">CalculateField wkr_BTW2002_gen LAND_NAME "Baden-Württemberg" VB #</Process><Process ToolSource="c:\program files (x86)\arcgis\desktop10.4\ArcToolbox\Toolboxes\Data Management Tools.tbx\CalculateField" Date="20161118" Time="083055">CalculateField wkr_BTW2002_gen LAND_NR "10" VB #</Process><Process ToolSource="c:\program files (x86)\arcgis\desktop10.4\ArcToolbox\Toolboxes\Data Management Tools.tbx\CalculateField" Date="20161118" Time="083117">CalculateField wkr_BTW2002_gen LAND_NAME "Saarland" VB #</Process><Process ToolSource="c:\program files (x86)\arcgis\desktop10.4\ArcToolbox\Toolboxes\Data Management Tools.tbx\CopyFeatures" Date="20161118" Time="083637">CopyFeatures D:\GIS_IT\Wahlen\Bundestagswahl2002\Geodaten\DatenBTW2002.gdb\wkr_BTW2002_gen D:\GIS_IT\Wahlen\Bundestagswahl2002\Geodaten\shapefiles\wkr_BTW2002_gen.shp # 0 0 0</Process><Process ToolSource="c:\program files (x86)\arcgis\desktop10.4\ArcToolbox\Toolboxes\Data Management Tools.tbx\DeleteField" Date="20161118" Time="104552">DeleteField D:\GIS_IT\Wahlen\Bundestagswahl2002\Geodaten\shapefiles\wkr_BTW2002_gen.shp Shape_Leng;Shape_Area</Process><Process ToolSource="c:\program files (x86)\arcgis\desktop10.4\ArcToolbox\Toolboxes\Data Management Tools.tbx\Rename" Date="20161118" Time="104800">Rename D:\GIS_IT\Wahlen\Bundestagswahl2002\Geodaten\shapefiles\wkr_BTW2002_gen.shp D:\GIS_IT\Wahlen\Bundestagswahl2002\Geodaten\shapefiles\Geometrie_Wahlkreise_15DBT.shp ShapeFile</Process><Process ToolSource="c:\program files (x86)\arcgis\desktop10.4\ArcToolbox\Toolboxes\Data Management Tools.tbx\Project" Date="20161130" Time="150015">Project D:\GIS_IT\Wahlen\Bundestagswahl2002\Geodaten\shapefiles\Geometrie_Wahlkreise_15DBT.shp D:\GIS_IT\Wahlen\Bundestagswahl2002\Geodaten\shapefiles\Geometrie_Wahlkreise_15DBT_geo.shp GEOGCS['GCS_WGS_1984',DATUM['D_WGS_1984',SPHEROID['WGS_1984',6378137.0,298.257223563]],PRIMEM['Greenwich',0.0],UNIT['Degree',0.0174532925199433]] ETRS_1989_To_WGS_1984 PROJCS['ETRS_1989_UTM_Zone_32N',GEOGCS['GCS_ETRS_1989',DATUM['D_ETRS_1989',SPHEROID['GRS_1980',6378137.0,298.257222101]],PRIMEM['Greenwich',0.0],UNIT['Degree',0.0174532925199433]],PROJECTION['Transverse_Mercator'],PARAMETER['False_Easting',500000.0],PARAMETER['False_Northing',0.0],PARAMETER['Central_Meridian',9.0],PARAMETER['Scale_Factor',0.9996],PARAMETER['Latitude_Of_Origin',0.0],UNIT['Meter',1.0]] NO_PRESERVE_SHAPE # NO_VERTICAL</Process></lineage><itemProps><itemLocation><linkage Sync="TRUE">file://\\SV-GIS-01\D$\GIS_IT\Wahlen\Bundestagswahl2002\Geodaten\shapefiles\wkr_BTW2002_gen.shp</linkage><protocol Sync="TRUE">Local Area Network</protocol></itemLocation><itemName Sync="TRUE">wkr_BTW2002_gen</itemName><imsContentType Sync="TRUE">002</imsContentType><itemSize Sync="TRUE">0.000</itemSize></itemProps><coordRef><type Sync="TRUE">Projected</type><geogcsn Sync="TRUE">GCS_ETRS_1989</geogcsn><csUnits Sync="TRUE">Linear Unit: Meter (1.000000)</csUnits><projcsn Sync="TRUE">ETRS_1989_UTM_Zone_32N</projcsn><peXml Sync="TRUE">&lt;ProjectedCoordinateSystem xsi:type='typens:ProjectedCoordinateSystem' xmlns:xsi='http://www.w3.org/2001/XMLSchema-instance' xmlns:xs='http://www.w3.org/2001/XMLSchema' xmlns:typens='http://www.esri.com/schemas/ArcGIS/10.4'&gt;&lt;WKT&gt;PROJCS[&amp;quot;ETRS_1989_UTM_Zone_32N&amp;quot;,GEOGCS[&amp;quot;GCS_ETRS_1989&amp;quot;,DATUM[&amp;quot;D_ETRS_1989&amp;quot;,SPHEROID[&amp;quot;GRS_1980&amp;quot;,6378137.0,298.257222101]],PRIMEM[&amp;quot;Greenwich&amp;quot;,0.0],UNIT[&amp;quot;Degree&amp;quot;,0.0174532925199433]],PROJECTION[&amp;quot;Transverse_Mercator&amp;quot;],PARAMETER[&amp;quot;False_Easting&amp;quot;,500000.0],PARAMETER[&amp;quot;False_Northing&amp;quot;,0.0],PARAMETER[&amp;quot;Central_Meridian&amp;quot;,9.0],PARAMETER[&amp;quot;Scale_Factor&amp;quot;,0.9996],PARAMETER[&amp;quot;Latitude_Of_Origin&amp;quot;,0.0],UNIT[&amp;quot;Meter&amp;quot;,1.0],AUTHORITY[&amp;quot;EPSG&amp;quot;,25832]]&lt;/WKT&gt;&lt;XOrigin&gt;-5120900&lt;/XOrigin&gt;&lt;YOrigin&gt;-9998100&lt;/YOrigin&gt;&lt;XYScale&gt;450445547.3910538&lt;/XYScale&gt;&lt;ZOrigin&gt;-100000&lt;/ZOrigin&gt;&lt;ZScale&gt;10000&lt;/ZScale&gt;&lt;MOrigin&gt;-100000&lt;/MOrigin&gt;&lt;MScale&gt;10000&lt;/MScale&gt;&lt;XYTolerance&gt;0.001&lt;/XYTolerance&gt;&lt;ZTolerance&gt;0.001&lt;/ZTolerance&gt;&lt;MTolerance&gt;0.001&lt;/MTolerance&gt;&lt;HighPrecision&gt;true&lt;/HighPrecision&gt;&lt;WKID&gt;25832&lt;/WKID&gt;&lt;LatestWKID&gt;25832&lt;/LatestWKID&gt;&lt;/ProjectedCoordinateSystem&gt;</peXml></coordRef></DataProperties><ArcGISFormat>1.0</ArcGISFormat><ArcGISstyle>FGDC CSDGM Metadata</ArcGISstyle></Esri><idinfo><native Sync="TRUE">Microsoft Windows 2000 Version 5.2 (Build 3790) Service Pack 2; ESRI ArcCatalog 9.3.1.1850</native><descript><langdata Sync="TRUE">de</langdata><abstract>REQUIRED: A brief narrative summary of the data set.</abstract><purpose>REQUIRED: A summary of the intentions with which the data set was developed.</purpose></descript><citation><citeinfo><origin>REQUIRED: The name of an organization or individual that developed the data set.</origin><pubdate>REQUIRED: The date when the data set is published or otherwise made available for release.</pubdate><title Sync="TRUE">gem1000_region_gem</title><ftname Sync="TRUE">gem1000_region_gem</ftname><geoform Sync="TRUE">vector digital data</geoform><onlink Sync="TRUE">\\SV-MS-05\D\Geodaten\Geometrien\Vermessungsverwaltung\Verwaltungsgebiete\Stichtag_20021231\Verwaltungsgebiete_1000.gdb</onlink></citeinfo></citation><timeperd><current>REQUIRED: The basis on which the time period of content information is determined.</current><timeinfo><sngdate><caldate>REQUIRED: The year (and optionally month, or month and day) for which the data set corresponds to the ground.</caldate></sngdate></timeinfo></timeperd><status><progress>REQUIRED: The state of the data set.</progress><update>REQUIRED: The frequency with which changes and additions are made to the data set after the initial data set is completed.</update></status><spdom><bounding><westbc Sync="TRUE">5.566085</westbc><eastbc Sync="TRUE">15.573716</eastbc><northbc Sync="TRUE">55.060444</northbc><southbc Sync="TRUE">47.141984</southbc></bounding><lboundng><leftbc Sync="TRUE">3280387.059100</leftbc><rightbc Sync="TRUE">3921542.706800</rightbc><bottombc Sync="TRUE">5237512.210100</bottombc><topbc Sync="TRUE">6103327.048700</topbc></lboundng></spdom><keywords><theme><themekt>REQUIRED: Reference to a formally registered thesaurus or a similar authoritative source of theme keywords.</themekt><themekey>REQUIRED: Common-use word or phrase used to describe the subject of the data set.</themekey></theme></keywords><accconst>REQUIRED: Restrictions and legal prerequisites for accessing the data set.</accconst><useconst>REQUIRED: Restrictions and legal prerequisites for using the data set after access is granted.</useconst><natvform Sync="TRUE">Feature-Class in File-Geodatabase</natvform></idinfo><dataIdInfo><envirDesc Sync="TRUE">Microsoft Windows Server 2008 R2 Version 6.1 (Build 7601) Service Pack 1; Esri ArcGIS 10.4.0.5524</envirDesc><dataLang><languageCode Sync="TRUE" value="deu"></languageCode><countryCode value="DEU" Sync="TRUE"></countryCode></dataLang><idCitation><resTitle Sync="TRUE">wkr_BTW2002_gen</resTitle><presForm><PresFormCd Sync="TRUE" value="005"></PresFormCd></presForm></idCitation><spatRpType><SpatRepTypCd Sync="TRUE" value="001"></SpatRepTypCd></spatRpType><dataExt><geoEle><GeoBndBox esriExtentType="native"><westBL Sync="TRUE">3280387.0591</westBL><eastBL Sync="TRUE">3921542.7068</eastBL><northBL Sync="TRUE">6103327.0487</northBL><southBL Sync="TRUE">5237512.2101</southBL><exTypeCode Sync="TRUE">1</exTypeCode></GeoBndBox></geoEle></dataExt><geoBox esriExtentType="decdegrees"><westBL Sync="TRUE">5.566085</westBL><eastBL Sync="TRUE">15.573716</eastBL><northBL Sync="TRUE">55.060444</northBL><southBL Sync="TRUE">47.141984</southBL><exTypeCode Sync="TRUE">1</exTypeCode></geoBox></dataIdInfo><metainfo><langmeta Sync="TRUE">de</langmeta><metstdn Sync="TRUE">FGDC Content Standards for Digital Geospatial Metadata</metstdn><metstdv Sync="TRUE">FGDC-STD-001-1998</metstdv><mettc Sync="TRUE">local time</mettc><metc><cntinfo><cntorgp><cntper>REQUIRED: The person responsible for the metadata information.</cntper><cntorg>REQUIRED: The organization responsible for the metadata information.</cntorg></cntorgp><cntaddr><addrtype>REQUIRED: The mailing and/or physical address for the organization or individual.</addrtype><city>REQUIRED: The city of the address.</city><state>REQUIRED: The state or province of the address.</state><postal>REQUIRED: The ZIP or other postal code of the address.</postal></cntaddr><cntvoice>REQUIRED: The telephone number by which individuals can speak to the organization or individual.</cntvoice></cntinfo></metc><metd Sync="TRUE">20101220</metd></metainfo><mdLang><languageCode Sync="TRUE" value="deu"></languageCode><countryCode value="DEU" Sync="TRUE"></countryCode></mdLang><mdStanName Sync="TRUE">ISO 19115 Geographic Information - Metadata</mdStanName><mdStanVer Sync="TRUE"># 11108</mdStanVer><mdChar><CharSetCd Sync="TRUE" value="# 11111"></CharSetCd></mdChar><mdHrLv><ScopeCd Sync="TRUE" value="005"></ScopeCd></mdHrLv><mdHrLvName Sync="TRUE">dataset</mdHrLvName><distinfo><resdesc Sync="TRUE">Downloadable Data</resdesc><stdorder><digform><digtinfo><transize Sync="TRUE">18,740</transize><dssize Sync="TRUE">18,740</dssize></digtinfo></digform></stdorder></distinfo><distInfo><distributor><distorTran><onLineSrc><orDesc Sync="TRUE">002</orDesc><linkage Sync="TRUE">file://\\SV-MS-05\D\Geodaten\Geometrien\Vermessungsverwaltung\Verwaltungsgebiete\Stichtag_20021231\Verwaltungsgebiete_1000.gdb</linkage><protocol Sync="TRUE">Local Area Network</protocol></onLineSrc><transSize Sync="TRUE">18,740</transSize></distorTran><distorFormat><formatName Sync="TRUE">Feature-Class in File-Geodatabase</formatName></distorFormat></distributor><distFormat><formatName Sync="TRUE">Shapefile</formatName></distFormat><distTranOps><transSize Sync="TRUE">0.000</transSize></distTranOps></distInfo><spdoinfo><direct Sync="TRUE">Vector</direct><ptvctinf><esriterm Name="wkr_BTW2002_gen"><efeatyp Sync="TRUE">Simple</efeatyp><efeageom code="4" Sync="TRUE"></efeageom><esritopo Sync="TRUE">FALSE</esritopo><efeacnt Sync="TRUE">0</efeacnt><spindex Sync="TRUE">FALSE</spindex><linrefer Sync="TRUE">FALSE</linrefer></esriterm></ptvctinf></spdoinfo><spref><horizsys><cordsysn><geogcsn Sync="TRUE">GCS_Deutsches_Hauptdreiecksnetz</geogcsn><projcsn Sync="TRUE">Germany_Zone_3</projcsn></cordsysn><planar><planci><plance Sync="TRUE">coordinate pair</plance><plandu Sync="TRUE">meters</plandu><coordrep><absres Sync="TRUE">0.000100</absres><ordres Sync="TRUE">0.000100</ordres></coordrep></planci></planar><geodetic><horizdn Sync="TRUE">D_Deutsches_Hauptdreiecksnetz</horizdn><ellips Sync="TRUE">Bessel_1841</ellips><semiaxis Sync="TRUE">6377397.155000</semiaxis><denflat Sync="TRUE">299.152813</denflat></geodetic></horizsys></spref><refSysInfo><RefSystem><refSysID><identCode Sync="TRUE" code="25832">Germany_Zone_3</identCode><idCodeSpace Sync="TRUE">EPSG</idCodeSpace><idVersion Sync="TRUE">5.1(4.0.0)</idVersion></refSysID></RefSystem></refSysInfo><spatRepInfo><VectSpatRep><geometObjs Name="wkr_BTW2002_gen"><geoObjTyp><GeoObjTypCd value="002" Sync="TRUE"></GeoObjTypCd></geoObjTyp><geoObjCnt Sync="TRUE">0</geoObjCnt></geometObjs><topLvl><TopoLevCd value="001" Sync="TRUE"></TopoLevCd></topLvl></VectSpatRep></spatRepInfo><eainfo><detailed Name="wkr_BTW2002_gen"><enttyp><enttypl Sync="TRUE">wkr_BTW2002_gen</enttypl><enttypt Sync="TRUE">Feature Class</enttypt><enttypc Sync="TRUE">0</enttypc></enttyp><attr><attrlabl Sync="TRUE">FID</attrlabl><attalias Sync="TRUE">FID</attalias><attrtype Sync="TRUE">OID</attrtype><attwidth Sync="TRUE">4</attwidth><atprecis Sync="TRUE">0</atprecis><attscale Sync="TRUE">0</attscale><attrdef Sync="TRUE">Internal feature number.</attrdef><attrdefs Sync="TRUE">Esri</attrdefs><attrdomv><udom Sync="TRUE">Sequential unique whole numbers that are automatically generated.</udom></attrdomv></attr><attr><attrlabl Sync="TRUE">Shape</attrlabl><attalias Sync="TRUE">Shape</attalias><attrtype Sync="TRUE">Geometry</attrtype><attwidth Sync="TRUE">0</attwidth><atprecis Sync="TRUE">0</atprecis><attscale Sync="TRUE">0</attscale><attrdef Sync="TRUE">Feature geometry.</attrdef><attrdefs Sync="TRUE">ESRI</attrdefs><attrdomv><udom Sync="TRUE">Coordinates defining the features.</udom></attrdomv></attr><attr><attrlabl Sync="TRUE">WKR_NR</attrlabl><attalias Sync="TRUE">WKR_NR</attalias><attrtype Sync="TRUE">Integer</attrtype><attwidth Sync="TRUE">5</attwidth><atprecis Sync="TRUE">5</atprecis><attscale Sync="TRUE">0</attscale></attr><attr><attrlabl Sync="TRUE">Shape_Leng</attrlabl><attalias Sync="TRUE">Shape_Leng</attalias><attrtype Sync="TRUE">Double</attrtype><attwidth Sync="TRUE">19</attwidth><atprecis Sync="TRUE">0</atprecis><attscale Sync="TRUE">0</attscale></attr><attr><attrlabl Sync="TRUE">Shape_Area</attrlabl><attalias Sync="TRUE">Shape_Area</attalias><attrtype Sync="TRUE">Double</attrtype><attwidth Sync="TRUE">19</attwidth><atprecis Sync="TRUE">0</atprecis><attscale Sync="TRUE">0</attscale><attrdef Sync="TRUE">Area of feature in internal units squared.</attrdef><attrdefs Sync="TRUE">ESRI</attrdefs><attrdomv><udom Sync="TRUE">Positive real numbers that are automatically generated.</udom></attrdomv></attr><attr><attrlabl Sync="TRUE">WKR_NAME</attrlabl><attalias Sync="TRUE">WKR_NAME</attalias><attrtype Sync="TRUE">String</attrtype><attwidth Sync="TRUE">90</attwidth><atprecis Sync="TRUE">0</atprecis><attscale Sync="TRUE">0</attscale></attr><attr><attrlabl Sync="TRUE">LAND_NR</attrlabl><attalias Sync="TRUE">LAND_NR</attalias><attrtype Sync="TRUE">String</attrtype><attwidth Sync="TRUE">2</attwidth><atprecis Sync="TRUE">0</atprecis><attscale Sync="TRUE">0</attscale></attr><attr><attrlabl Sync="TRUE">LAND_NAME</attrlabl><attalias Sync="TRUE">LAND_NAME</attalias><attrtype Sync="TRUE">String</attrtype><attwidth Sync="TRUE">25</attwidth><atprecis Sync="TRUE">0</atprecis><attscale Sync="TRUE">0</attscale></attr></detailed><detailed Name="gem1000.pat"><enttyp><enttypl Sync="TRUE">gem1000.pat</enttypl><enttypt Sync="TRUE">Feature Class</enttypt><enttypc Sync="TRUE">14048</enttypc></enttyp><attr><attrlabl Sync="TRUE">FID</attrlabl><attalias Sync="TRUE">FID</attalias><attrtype Sync="TRUE">OID</attrtype><attwidth Sync="TRUE">4</attwidth><atprecis Sync="TRUE">0</atprecis><attscale Sync="TRUE">0</attscale><attrdef Sync="TRUE">Internal feature number.</attrdef><attrdefs Sync="TRUE">ESRI</attrdefs><attrdomv><udom Sync="TRUE">Sequential unique whole numbers that are automatically generated.</udom></attrdomv></attr><attr><attrlabl Sync="TRUE">Shape</attrlabl><attalias Sync="TRUE">Shape</attalias><attrtype Sync="TRUE">Geometry</attrtype><attwidth Sync="TRUE">0</attwidth><atprecis Sync="TRUE">0</atprecis><attscale Sync="TRUE">0</attscale><attrdef Sync="TRUE">Feature geometry.</attrdef><attrdefs Sync="TRUE">ESRI</attrdefs><attrdomv><udom Sync="TRUE">Coordinates defining the features.</udom></attrdomv></attr><attr><attrlabl Sync="TRUE">AREA</attrlabl><attwidth Sync="TRUE">8</attwidth><atoutwid Sync="TRUE">18</atoutwid><attrtype Sync="TRUE">Float</attrtype><atnumdec Sync="TRUE">5</atnumdec><attrdef Sync="TRUE">Area of feature in internal units squared.</attrdef><attrdefs Sync="TRUE">ESRI</attrdefs><attrdomv><udom Sync="TRUE">Positive real numbers that are automatically generated.</udom></attrdomv></attr><attr><attrlabl Sync="TRUE">PERIMETER</attrlabl><attwidth Sync="TRUE">8</attwidth><atoutwid Sync="TRUE">18</atoutwid><attrtype Sync="TRUE">Float</attrtype><atnumdec Sync="TRUE">5</atnumdec><attrdef Sync="TRUE">Perimeter of feature in internal units.</attrdef><attrdefs Sync="TRUE">ESRI</attrdefs><attrdomv><udom Sync="TRUE">Positive real numbers that are automatically generated.</udom></attrdomv></attr><attr><attrlabl Sync="TRUE">GEM1000#</attrlabl><attwidth Sync="TRUE">4</attwidth><atoutwid Sync="TRUE">5</atoutwid><attrtype Sync="TRUE">Binary</attrtype><attrdef Sync="TRUE">Internal feature number.</attrdef><attrdefs Sync="TRUE">ESRI</attrdefs><attrdomv><udom Sync="TRUE">Sequential unique whole numbers that are automatically generated.</udom></attrdomv></attr><attr><attrlabl Sync="TRUE">GEM1000-ID</attrlabl><attwidth Sync="TRUE">4</attwidth><atoutwid Sync="TRUE">5</atoutwid><attrtype Sync="TRUE">Binary</attrtype><attrdef Sync="TRUE">User-defined feature number.</attrdef><attrdefs Sync="TRUE">ESRI</attrdefs></attr><attr><attrlabl Sync="TRUE">SHN</attrlabl><attwidth Sync="TRUE">12</attwidth><atoutwid Sync="TRUE">12</atoutwid><attrtype Sync="TRUE">Character</attrtype></attr><attr><attrlabl Sync="TRUE">MOC</attrlabl><attwidth Sync="TRUE">3</attwidth><atoutwid Sync="TRUE">3</atoutwid><attrtype Sync="TRUE">Integer</attrtype></attr><attr><attrlabl Sync="TRUE">RAU</attrlabl><attwidth Sync="TRUE">12</attwidth><atoutwid Sync="TRUE">12</atoutwid><attrtype Sync="TRUE">Character</attrtype></attr><attr><attrlabl Sync="TRUE">USE</attrlabl><attwidth Sync="TRUE">2</attwidth><atoutwid Sync="TRUE">2</atoutwid><attrtype Sync="TRUE">Integer</attrtype></attr><attr><attrlabl Sync="TRUE">KEY</attrlabl><attwidth Sync="TRUE">8</attwidth><atoutwid Sync="TRUE">8</atoutwid><attrtype Sync="TRUE">Character</attrtype></attr><attr><attrlabl Sync="TRUE">GEN</attrlabl><attwidth Sync="TRUE">50</attwidth><atoutwid Sync="TRUE">50</atoutwid><attrtype Sync="TRUE">Character</attrtype></attr><attr><attrlabl Sync="TRUE">EWZ</attrlabl><attwidth Sync="TRUE">8</attwidth><atoutwid Sync="TRUE">10</atoutwid><attrtype Sync="TRUE">Float</attrtype><atnumdec Sync="TRUE">0</atnumdec></attr><attr><attrlabl Sync="TRUE">DES</attrlabl><attwidth Sync="TRUE">50</attwidth><atoutwid Sync="TRUE">50</atoutwid><attrtype Sync="TRUE">Character</attrtype></attr></detailed><detailed Name="gem1000.nat"><enttyp><enttypl Sync="TRUE">gem1000.nat</enttypl><enttypt Sync="TRUE">Feature Class</enttypt><enttypc Sync="TRUE">28281</enttypc></enttyp><attr><attrlabl Sync="TRUE">FID</attrlabl><attalias Sync="TRUE">FID</attalias><attrtype Sync="TRUE">OID</attrtype><attwidth Sync="TRUE">4</attwidth><atprecis Sync="TRUE">0</atprecis><attscale Sync="TRUE">0</attscale><attrdef Sync="TRUE">Internal feature number.</attrdef><attrdefs Sync="TRUE">ESRI</attrdefs><attrdomv><udom Sync="TRUE">Sequential unique whole numbers that are automatically generated.</udom></attrdomv></attr><attr><attrlabl Sync="TRUE">Shape</attrlabl><attalias Sync="TRUE">Shape</attalias><attrtype Sync="TRUE">Geometry</attrtype><attwidth Sync="TRUE">0</attwidth><atprecis Sync="TRUE">0</atprecis><attscale Sync="TRUE">0</attscale><attrdef Sync="TRUE">Feature geometry.</attrdef><attrdefs Sync="TRUE">ESRI</attrdefs><attrdomv><udom Sync="TRUE">Coordinates defining the features.</udom></attrdomv></attr><attr><attrlabl Sync="TRUE">ARC#</attrlabl><attwidth Sync="TRUE">4</attwidth><atoutwid Sync="TRUE">5</atoutwid><attrtype Sync="TRUE">Binary</attrtype></attr><attr><attrlabl Sync="TRUE">GEM1000#</attrlabl><attwidth Sync="TRUE">4</attwidth><atoutwid Sync="TRUE">5</atoutwid><attrtype Sync="TRUE">Binary</attrtype><attrdef Sync="TRUE">Internal feature number.</attrdef><attrdefs Sync="TRUE">ESRI</attrdefs><attrdomv><udom Sync="TRUE">Sequential unique whole numbers that are automatically generated.</udom></attrdomv></attr><attr><attrlabl Sync="TRUE">GEM1000-ID</attrlabl><attwidth Sync="TRUE">4</attwidth><atoutwid Sync="TRUE">5</atoutwid><attrtype Sync="TRUE">Binary</attrtype><attrdef Sync="TRUE">User-defined feature number.</attrdef><attrdefs Sync="TRUE">ESRI</attrdefs></attr></detailed><detailed Name="gem1000.patgem"><enttyp><enttypl Sync="TRUE">gem1000.patgem</enttypl><enttypt Sync="TRUE">Feature Class</enttypt><enttypc Sync="TRUE">13409</enttypc></enttyp><attr><attrlabl Sync="TRUE">FID</attrlabl><attalias Sync="TRUE">FID</attalias><attrtype Sync="TRUE">OID</attrtype><attwidth Sync="TRUE">4</attwidth><atprecis Sync="TRUE">0</atprecis><attscale Sync="TRUE">0</attscale><attrdef Sync="TRUE">Internal feature number.</attrdef><attrdefs Sync="TRUE">ESRI</attrdefs><attrdomv><udom Sync="TRUE">Sequential unique whole numbers that are automatically generated.</udom></attrdomv></attr><attr><attrlabl Sync="TRUE">Shape</attrlabl><attalias Sync="TRUE">Shape</attalias><attrtype Sync="TRUE">Geometry</attrtype><attwidth Sync="TRUE">0</attwidth><atprecis Sync="TRUE">0</atprecis><attscale Sync="TRUE">0</attscale><attrdef Sync="TRUE">Feature geometry.</attrdef><attrdefs Sync="TRUE">ESRI</attrdefs><attrdomv><udom Sync="TRUE">Coordinates defining the features.</udom></attrdomv></attr><attr><attrlabl Sync="TRUE">AREA</attrlabl><attwidth Sync="TRUE">8</attwidth><atoutwid Sync="TRUE">18</atoutwid><attrtype Sync="TRUE">Float</attrtype><atnumdec Sync="TRUE">5</atnumdec><attrdef Sync="TRUE">Area of feature in internal units squared.</attrdef><attrdefs Sync="TRUE">ESRI</attrdefs><attrdomv><udom Sync="TRUE">Positive real numbers that are automatically generated.</udom></attrdomv></attr><attr><attrlabl Sync="TRUE">PERIMETER</attrlabl><attwidth Sync="TRUE">8</attwidth><atoutwid Sync="TRUE">18</atoutwid><attrtype Sync="TRUE">Float</attrtype><atnumdec Sync="TRUE">5</atnumdec><attrdef Sync="TRUE">Perimeter of feature in internal units.</attrdef><attrdefs Sync="TRUE">ESRI</attrdefs><attrdomv><udom Sync="TRUE">Positive real numbers that are automatically generated.</udom></attrdomv></attr><attr><attrlabl Sync="TRUE">GEM#</attrlabl><attwidth Sync="TRUE">4</attwidth><atoutwid Sync="TRUE">5</atoutwid><attrtype Sync="TRUE">Binary</attrtype><attrdef Sync="TRUE">Internal feature number.</attrdef><attrdefs Sync="TRUE">ESRI</attrdefs><attrdomv><udom Sync="TRUE">Sequential unique whole numbers that are automatically generated.</udom></attrdomv></attr><attr><attrlabl Sync="TRUE">GEM-ID</attrlabl><attwidth Sync="TRUE">4</attwidth><atoutwid Sync="TRUE">5</atoutwid><attrtype Sync="TRUE">Binary</attrtype><attrdef Sync="TRUE">User-defined feature number.</attrdef><attrdefs Sync="TRUE">ESRI</attrdefs></attr><attr><attrlabl Sync="TRUE">SHN</attrlabl><attwidth Sync="TRUE">12</attwidth><atoutwid Sync="TRUE">12</atoutwid><attrtype Sync="TRUE">Character</attrtype></attr><attr><attrlabl Sync="TRUE">RAU</attrlabl><attwidth Sync="TRUE">12</attwidth><atoutwid Sync="TRUE">12</atoutwid><attrtype Sync="TRUE">Character</attrtype></attr><attr><attrlabl Sync="TRUE">USE</attrlabl><attwidth Sync="TRUE">2</attwidth><atoutwid Sync="TRUE">2</atoutwid><attrtype Sync="TRUE">Integer</attrtype></attr><attr><attrlabl Sync="TRUE">KEY</attrlabl><attwidth Sync="TRUE">8</attwidth><atoutwid Sync="TRUE">8</atoutwid><attrtype Sync="TRUE">Character</attrtype></attr><attr><attrlabl Sync="TRUE">GEN</attrlabl><attwidth Sync="TRUE">50</attwidth><atoutwid Sync="TRUE">50</atoutwid><attrtype Sync="TRUE">Character</attrtype></attr><attr><attrlabl Sync="TRUE">EWZ</attrlabl><attwidth Sync="TRUE">8</attwidth><atoutwid Sync="TRUE">10</atoutwid><attrtype Sync="TRUE">Float</attrtype><atnumdec Sync="TRUE">0</atnumdec></attr><attr><attrlabl Sync="TRUE">DES</attrlabl><attwidth Sync="TRUE">50</attwidth><atoutwid Sync="TRUE">50</atoutwid><attrtype Sync="TRUE">Character</attrtype></attr><attr><attrlabl Sync="TRUE">FLAECHE_IN_QKM</attrlabl><attwidth Sync="TRUE">4</attwidth><atoutwid Sync="TRUE">12</atoutwid><attrtype Sync="TRUE">Float</attrtype><atnumdec Sync="TRUE">3</atnumdec></attr></detailed></eainfo><mdDateSt Sync="TRUE">20161118</mdDateSt><dataqual><lineage><procstep><procdesc Sync="TRUE">Dataset kopiert.</procdesc><srcused Sync="TRUE">\\SV-MS-05\D\Temp\temp_kk\Geometrien\Stichtag_20021231\vg1000.gdb</srcused><procdate Sync="TRUE">20101220</procdate><proctime Sync="TRUE">09113200</proctime></procstep></lineage></dataqual></metadata>
